karas/__init__.py
karas/dataloader.py
karas/reporter.py
karas/version.py
karas/iterators/__init__.py
karas/iterators/iterator.py
karas/training/__init__.py
karas/training/extension.py
karas/training/trainer.py
karas/training/trigger.py
karas/training/updater.py
karas/training/utils.py
karas/training/extensions/__init__.py
karas/training/extensions/log_report.py
karas/training/extensions/lr_observer.py
karas/training/extensions/lr_scheduler.py
karas/training/extensions/print_report.py
karas/training/extensions/progress_bar.py
karas/training/extensions/snapshot.py
karas/training/extensions/tensorboard.py
karas/training/triggers/__init__.py
karas/training/triggers/best_value_trigger.py
karas/training/triggers/early_stopping_trigger.py
karas/training/triggers/interval_trigger.py
karas/training/triggers/utils.py
test/__init__.py
test/extension.py
test/load.py
test/main.py
test/net.py
test/updater.py
karas-0.7.0.dist-info/LICENSE
karas-0.7.0.dist-info/METADATA
karas-0.7.0.dist-info/WHEEL
karas-0.7.0.dist-info/top_level.txt
karas-0.7.0.dist-info/RECORD
